litex.novitus_xml-1.0.0-py3.8-nspkg.pth
litex/novitus_xml/__init__.py
litex/novitus_xml/exceptions.py
litex/novitus_xml/helpers.py
litex/novitus_xml/printer.py
litex.novitus_xml-1.0.0.dist-info/LICENSE
litex.novitus_xml-1.0.0.dist-info/METADATA
litex.novitus_xml-1.0.0.dist-info/WHEEL
litex.novitus_xml-1.0.0.dist-info/namespace_packages.txt
litex.novitus_xml-1.0.0.dist-info/top_level.txt
litex.novitus_xml-1.0.0.dist-info/RECORD
