Metadata-Version: 2.1
Name: litex.novitus-xml
Version: 1.0.0
Summary: A Novitus XML Protocol Fiscal Printer Library
Home-page: UNKNOWN
Author: Michał Węgrzynek
Author-email: mwegrzynek@litexservice.pl
License: UNKNOWN
Platform: UNKNOWN
Classifier: Programming Language :: Python :: 3
Classifier: License :: OSI Approved :: GNU Lesser General Public License v3 or later (LGPLv3+)
Classifier: Operating System :: OS Independent
Classifier: Topic :: System :: Hardware :: Hardware Drivers
Classifier: Topic :: Office/Business :: Financial
Classifier: Topic :: Software Development :: Libraries
Requires-Dist: pyserial
Requires-Dist: lxml
